[
    {
        "tweet_count": 0,
        "user_name": "@dswdserves",
        "text": "HAPPENING NOW: Kasalukuyang ikinakarga ang 5,500 kahon ng family food packs (FFPs) sa BRP Teresa Magbanua ng Philippine Coast Guard (PCG) patungong Batanes ngayong Miyerkules (Mayo 27). Ito ay bilang pagtiyak na may naka-prepositioned na mga FFPs sa iba't ibang warehouse sa bansa https://t.co/1SfZkbyG9I",
        "created_at": "Tue May 27 03:39:01 +0000 2025",
        "reposts_count": 0,
        "likes_count": 0,
        "replies_count": 0
    },
    {
        "tweet_count": 1,
        "user_name": "Philippine Red Cross",
        "text": "ğ— ğ—®ğ—´ğ—¶ğ—»ğ—´ ğ—¥ğ—²ğ—± ğ—–ğ—¿ğ—¼ğ˜€ğ˜€ ğ—¿ğ—²ğ—®ğ—±ğ˜†!\n\nLaging maghanda ng go-bag kung saan nakalagay ang mga pangunahing pangangailangan kung sakaling magkaroon ng evacuation. Maghanda ng mga gamit at pagkain na maaaring tumagal hanggang 72-hours para sa buong pamilya.\n\n#KristinePH https://t.co/n92roSIrDo",
        "created_at": "Fri Oct 25 02:53:19 +0000 2024",
        "reposts_count": 603,
        "likes_count": 2800,
        "replies_count": 1
    }
]